mosi/__init__.py
mosi/clii/__init__.py
mosi/clii/_cli.py
mosi/clii/_lp.py
mosi/clii/_lps.py
mosi/clii/_mps.py
mosi/clii/_serializers.py
mosi/clii/_solution.py
mosi/common/__init__.py
mosi/common/_enums.py
mosi/common/_exceptions.py
mosi/common/_objects.py
mosi/common/_utils.py
mosi/lp/__init__.py
mosi/lp/_constraint.py
mosi/lp/_model.py
mosi/lp/_objective.py
mosi/lp/_sum.py
mosi/lp/_variable.py
mosi/solver/__init__.py
mosi/solver/_base.py
mosi/solver/_cbc.py
mosi/solver/_cplex.py
mosi/solver/_glpk.py
mosi/solver/_lp_solve.py
mosi-0.0.3.dist-info/DESCRIPTION.rst
mosi-0.0.3.dist-info/METADATA
mosi-0.0.3.dist-info/RECORD
mosi-0.0.3.dist-info/WHEEL
mosi-0.0.3.dist-info/metadata.json
mosi-0.0.3.dist-info/top_level.txt
